gsalib.py
gsalib-1.0.6.dist-info/DESCRIPTION.rst
gsalib-1.0.6.dist-info/METADATA
gsalib-1.0.6.dist-info/RECORD
gsalib-1.0.6.dist-info/WHEEL
gsalib-1.0.6.dist-info/metadata.json
gsalib-1.0.6.dist-info/top_level.txt
