Metadata-Version: 2.0
Name: gsalib
Version: 1.0.6
Summary: Python version of R gsalib to read GATK Report tables into pandas DataFrames
Home-page: https://github.com/myourshaw/gsalib
Author: Michael Yourshaw
Author-email: myourshaw@gmail.com
License: MIT License
Project-URL: Bug Reports, https://github.com/myourshaw/gsalib/issues
Project-URL: Funding, https://donate.pypi.org
Project-URL: Say Thanks!, https://cran.r-project.org/web/packages/gsalib/index.html
Project-URL: Source, https://github.com/myourshaw/gsalib/
Project-URL: Documentation, https://gsalib.readthedocs.io/en/latest/
Keywords: gsalib GATK report table R pandas DataFrame
Platform: UNKNOWN
Classifier: Development Status :: 5 - Production/Stable
Classifier: Intended Audience :: Science/Research
Classifier: Topic :: Scientific/Engineering :: Bio-Informatics
Classifier: License :: OSI Approved :: MIT License
Classifier: Programming Language :: Python :: 2
Classifier: Programming Language :: Python :: 2.7
Classifier: Programming Language :: Python :: 3
Classifier: Programming Language :: Python :: 3.4
Classifier: Programming Language :: Python :: 3.5
Classifier: Programming Language :: Python :: 3.6
Requires-Dist: pandas
